MANIFEST.in
setup.py
collective/__init__.py
collective.validator.base.egg-info/PKG-INFO
collective.validator.base.egg-info/SOURCES.txt
collective.validator.base.egg-info/dependency_links.txt
collective.validator.base.egg-info/entry_points.txt
collective.validator.base.egg-info/namespace_packages.txt
collective.validator.base.egg-info/not-zip-safe
collective.validator.base.egg-info/requires.txt
collective.validator.base.egg-info/top_level.txt
collective/validator/__init__.py
collective/validator/base/HISTORY.txt
collective/validator/base/README.txt
collective/validator/base/__init__.py
collective/validator/base/config.py
collective/validator/base/configure.zcml
collective/validator/base/permissions.py
collective/validator/base/profiles.zcml
collective/validator/base/setuphandlers.py
collective/validator/base/utility.py
collective/validator/base/Extensions/install.py
collective/validator/base/browser/__init__.py
collective/validator/base/browser/adapter.py
collective/validator/base/browser/config_control-panel.pt
collective/validator/base/browser/configure.zcml
collective/validator/base/browser/folder_report.pt
collective/validator/base/browser/folder_report.py
collective/validator/base/browser/remote_validation.pt
collective/validator/base/browser/remote_validation.py
collective/validator/base/browser/validate_xhtml_form.pt
collective/validator/base/browser/validate_xhtml_form.py
collective/validator/base/browser/validationtool.py
collective/validator/base/browser/valtool_control-panel.pt
collective/validator/base/browser/vt_view.py
collective/validator/base/content/ATFileReport.py
collective/validator/base/content/ATReport.py
collective/validator/base/content/ValidationTool.py
collective/validator/base/content/__init__.py
collective/validator/base/content/basecontentvalidable.py
collective/validator/base/content/configure.zcml
collective/validator/base/content/sendattachment.py
collective/validator/base/i18n/collective.validator.base-it.po
collective/validator/base/i18n/plone.po
collective/validator/base/interfaces/__init__.py
collective/validator/base/interfaces/configure.zcml
collective/validator/base/interfaces/interfaces.py
collective/validator/base/interfaces/vocabolario.py
collective/validator/base/profiles/default/actionicons.xml
collective/validator/base/profiles/default/actions.xml
collective/validator/base/profiles/default/controlpanel.xml
