Metadata-Version: 1.1
Name: collective.validator.base
Version: 2.2.1
Summary: A Plone pages validator
Home-page: https://svn.plone.org/svn/collective/collective.validator.base
Author: RedTurtle Technology
Author-email: sviluppoplone@redturtle.it
License: GPL
Keywords: Plone Validator XHTML CSS
Platform: UNKNOWN
Classifier: Framework :: Plone
Classifier: Framework :: Zope2
Classifier: Framework :: Zope3
Classifier: Programming Language :: Python
Classifier: Topic :: Software Development :: Libraries :: Python Modules
